[
  {
    "question": "Two teammates are arguing over a project direction. What should you do first?",
    "answers": [
      {
        "text": "Ignore them",
        "score": 0
      },
      {
        "text": "Tell them to figure it out later",
        "score": 0
      },
      {
        "text": "Help mediate a calm discussion to clarify perspectives",
        "score": 1
      },
      {
        "text": "Choose a side immediately",
        "score": 0
      }
    ]
  },
  {
    "question": "What role does curiosity play in resolving conflict?",
    "answers": [
      {
        "text": "It makes things worse",
        "score": 0
      },
      {
        "text": "It delays resolution",
        "score": 0
      },
      {
        "text": "It helps you understand root causes",
        "score": 1
      },
      {
        "text": "It weakens your argument",
        "score": 0
      }
    ]
  },
  {
    "question": "Which skill supports productive conflict resolution?",
    "answers": [
      {
        "text": "Defensiveness",
        "score": 0
      },
      {
        "text": "Listening and reframing",
        "score": 1
      },
      {
        "text": "Avoidance",
        "score": 0
      },
      {
        "text": "Perfectionism",
        "score": 0
      }
    ]
  },
  {
    "question": "In conflict, why is it important to separate intent from impact?",
    "answers": [
      {
        "text": "So you can judge faster",
        "score": 0
      },
      {
        "text": "Because it makes feedback easier",
        "score": 0
      },
      {
        "text": "To understand how actions are perceived regardless of intent",
        "score": 1
      },
      {
        "text": "It doesn\u2019t matter",
        "score": 0
      }
    ]
  },
  {
    "question": "Someone reacts emotionally to a small issue. What might be behind it?",
    "answers": [
      {
        "text": "They are unstable",
        "score": 0
      },
      {
        "text": "They just want attention",
        "score": 0
      },
      {
        "text": "There may be a deeper unresolved concern",
        "score": 1
      },
      {
        "text": "They always react like that",
        "score": 0
      }
    ]
  }
]